STS/Buffer.py
STS/SSH.py
STS/Serial.py
STS/Telnet.py
STS/__init__.py
STS_connection-0.0.3.dist-info/METADATA
STS_connection-0.0.3.dist-info/WHEEL
STS_connection-0.0.3.dist-info/top_level.txt
STS_connection-0.0.3.dist-info/RECORD
